python_xbus-0.4.0.dist-info/licenses/LICENSE
xbus/__init__.py
xbus/actor_processing_context.py
xbus/checksum.py
xbus/cli.py
xbus/client.py
xbus/conn.py
xbus/control_nrpc.py
xbus/control_pb2.py
xbus/control_pb2.pyi
xbus/envelope_receiver.py
xbus/envelope_writer.py
xbus/fullenv.py
xbus/service.py
xbus/testutils.py
xbus/xbus_nrpc.py
xbus/xbus_pb2.py
xbus/xbus_pb2.pyi
xbus/demo/__init__.py
xbus/demo/helloworld.py
xbus/demo/print_to_console.py
xbus/demo/relay.py
python_xbus-0.4.0.dist-info/METADATA
python_xbus-0.4.0.dist-info/WHEEL
python_xbus-0.4.0.dist-info/entry_points.txt
python_xbus-0.4.0.dist-info/top_level.txt
python_xbus-0.4.0.dist-info/RECORD
