Metadata-Version: 2.4
Name: python-xbus
Version: 0.4.0
Summary: A python client for Xbus (https://xbus.io)
Home-page: https://bitbucket.org/orus-io/python-xbus
Maintainer: xbus.io
Maintainer-email: contact@xbus.io
License-File: LICENSE
Requires-Dist: crccheck
Requires-Dist: python-nrpc>=0.0.8
Requires-Dist: pyyaml
Requires-Dist: protobuf
Dynamic: description
Dynamic: home-page
Dynamic: license-file
Dynamic: maintainer
Dynamic: maintainer-email
Dynamic: requires-dist
Dynamic: summary
